ChengxuyuanMianshiJindianDiliubanQuanjieDoocsKaiyuanShequ/README.md
ChengxuyuanMianshiJindianDiliubanQuanjieDoocsKaiyuanShequ/__init__.py
ChengxuyuanMianshiJindianDiliubanQuanjieDoocsKaiyuanShequ/__main__.py
ChengxuyuanMianshiJindianDiliubanQuanjieDoocsKaiyuanShequ/file.epub
ChengxuyuanMianshiJindianDiliubanQuanjieDoocsKaiyuanShequ/index.html
ChengxuyuanMianshiJindianDiliubanQuanjieDoocsKaiyuanShequ/css/__init__.py
ChengxuyuanMianshiJindianDiliubanQuanjieDoocsKaiyuanShequ/css/annotations.css
ChengxuyuanMianshiJindianDiliubanQuanjieDoocsKaiyuanShequ/css/main.css
ChengxuyuanMianshiJindianDiliubanQuanjieDoocsKaiyuanShequ/css/normalize.css
ChengxuyuanMianshiJindianDiliubanQuanjieDoocsKaiyuanShequ/css/popup.css
ChengxuyuanMianshiJindianDiliubanQuanjieDoocsKaiyuanShequ/font/__init__.py
ChengxuyuanMianshiJindianDiliubanQuanjieDoocsKaiyuanShequ/font/fontello.eot
ChengxuyuanMianshiJindianDiliubanQuanjieDoocsKaiyuanShequ/font/fontello.svg
ChengxuyuanMianshiJindianDiliubanQuanjieDoocsKaiyuanShequ/font/fontello.ttf
ChengxuyuanMianshiJindianDiliubanQuanjieDoocsKaiyuanShequ/font/fontello.woff
ChengxuyuanMianshiJindianDiliubanQuanjieDoocsKaiyuanShequ/img/__init__.py
ChengxuyuanMianshiJindianDiliubanQuanjieDoocsKaiyuanShequ/img/annotator-glyph-sprite.png
ChengxuyuanMianshiJindianDiliubanQuanjieDoocsKaiyuanShequ/img/annotator-icon-sprite.png
ChengxuyuanMianshiJindianDiliubanQuanjieDoocsKaiyuanShequ/img/apple-touch-icon.png
ChengxuyuanMianshiJindianDiliubanQuanjieDoocsKaiyuanShequ/img/cancelfullscreen.png
ChengxuyuanMianshiJindianDiliubanQuanjieDoocsKaiyuanShequ/img/close.png
ChengxuyuanMianshiJindianDiliubanQuanjieDoocsKaiyuanShequ/img/fullscreen.png
ChengxuyuanMianshiJindianDiliubanQuanjieDoocsKaiyuanShequ/img/loader.gif
ChengxuyuanMianshiJindianDiliubanQuanjieDoocsKaiyuanShequ/img/menu-icon.png
ChengxuyuanMianshiJindianDiliubanQuanjieDoocsKaiyuanShequ/img/save.png
ChengxuyuanMianshiJindianDiliubanQuanjieDoocsKaiyuanShequ/img/saved.png
chengxuyuan_mianshi_jindian_diliuban_quanjie_doocs_kaiyuan_shequ-2024.3.5.0.dist-info/METADATA
chengxuyuan_mianshi_jindian_diliuban_quanjie_doocs_kaiyuan_shequ-2024.3.5.0.dist-info/WHEEL
chengxuyuan_mianshi_jindian_diliuban_quanjie_doocs_kaiyuan_shequ-2024.3.5.0.dist-info/entry_points.txt
chengxuyuan_mianshi_jindian_diliuban_quanjie_doocs_kaiyuan_shequ-2024.3.5.0.dist-info/top_level.txt
chengxuyuan_mianshi_jindian_diliuban_quanjie_doocs_kaiyuan_shequ-2024.3.5.0.dist-info/RECORD
